mcpv/__init__.py
mcpv/__main__.py
mcpv/dashboard.py
mcpv/main.py
mcpv/server.py
mcpv/valve.py
mcpv/vault.py
mcpv-0.3.5.dist-info/METADATA
mcpv-0.3.5.dist-info/WHEEL
mcpv-0.3.5.dist-info/entry_points.txt
mcpv-0.3.5.dist-info/RECORD
