Metadata-Version: 2.4
Name: mcpv
Version: 0.3.5
Summary: MCP Vault: Secure Gateway & Booster for Antigravity
Requires-Python: >=3.10
Requires-Dist: fastmcp>=0.1.0
Requires-Dist: mcp>=1.0.0
Requires-Dist: typer>=0.9.0
